accorder/__init__.py
accorder/assets/BROWSE_LIBRARY.html
accorder/assets/static/data1.js
accorder/assets/static/css/bundle.css
accorder/assets/static/css/bundle.css.map
accorder/assets/static/favicons/android-chrome-192x192.png
accorder/assets/static/favicons/android-chrome-512x512.png
accorder/assets/static/favicons/apple-touch-icon.png
accorder/assets/static/favicons/favicon-16x16.png
accorder/assets/static/favicons/favicon-32x32.png
accorder/assets/static/favicons/mstile-150x150.png
accorder/assets/static/favicons/safari-pinned-tab.svg
accorder/assets/static/fonts/IBMPlexMono-Bold.woff2
accorder/assets/static/fonts/IBMPlexMono-Italic.woff2
accorder/assets/static/fonts/IBMPlexMono-Regular.woff2
accorder/assets/static/fonts/IBMPlexMono.woff2
accorder/assets/static/js/bundle.js
accorder/assets/static/js/bundle.js.map
accorder/utils/__init__.py
accorder/utils/bibtex.py
accorder/utils/builds.py
accorder/utils/configs.py
accorder/utils/configurations.py
accorder/utils/cover.py
accorder/utils/motw_client.py
accorder/utils/submits.py
accorder/utils/uploads.py
accorder-21.5.4.dist-info/METADATA
accorder-21.5.4.dist-info/WHEEL
accorder-21.5.4.dist-info/entry_points.txt
accorder-21.5.4.dist-info/top_level.txt
accorder-21.5.4.dist-info/RECORD
