Metadata-Version: 2.1
Name: accorder
Version: 21.5.4
Summary: Accorder makes Calibre library portable as standalone webapp and ready to be shared at Memory of the World Library.
Home-page: UNKNOWN
Author: Marcell Mars
Author-email: ki.ber@kom.uni.st
License: UNKNOWN
Platform: UNKNOWN
Classifier: Development Status :: 4 - Beta
Classifier: Intended Audience :: Other Audience
Classifier: License :: OSI Approved :: GNU General Public License v3 or later (GPLv3+)
Classifier: Programming Language :: Python :: 3 :: Only
Classifier: Environment :: Console
Classifier: Topic :: Communications :: File Sharing
Requires-Python: >=3.6
Requires-Dist: Click
Requires-Dist: dataclasses
Requires-Dist: setuptools
Requires-Dist: pybtex
